fastjsondiff-0.1.0.dist-info/METADATA
fastjsondiff-0.1.0.dist-info/WHEEL
fastjsondiff-0.1.0.dist-info/licenses/LICENSE
fastjsondiff/__init__.py
fastjsondiff/fastjsondiff.cpython-312-darwin.so
fastjsondiff-0.1.0.dist-info/RECORD
