Metadata-Version: 2.4
Name: fastjsondiff
Version: 0.1.0
Classifier: Development Status :: 4 - Beta
Classifier: Intended Audience :: Developers
Classifier: License :: OSI Approved :: MIT License
Classifier: Operating System :: OS Independent
Classifier: Programming Language :: Python :: 3
Classifier: Programming Language :: Python :: 3.8
Classifier: Programming Language :: Python :: 3.9
Classifier: Programming Language :: Python :: 3.10
Classifier: Programming Language :: Python :: 3.11
Classifier: Programming Language :: Python :: 3.12
Classifier: Programming Language :: Rust
Classifier: Topic :: Software Development :: Libraries :: Python Modules
Classifier: Topic :: Software Development :: Testing
Classifier: Topic :: Text Processing
License-File: LICENSE
Summary: Fast JSON difference detection library with path-based filtering
Keywords: json,diff,comparison,rust,fast,performance
Author-email: Karthik M Prakash <mkarthikprakash.work@gmail.com>
Maintainer-email: Karthik M Prakash <mkarthikprakash.work@gmail.com>
License: MIT
Requires-Python: >=3.8
Project-URL: Repository, https://github.com/yourusername/fastjsondiff
